{
  "v": "5.9.0",
  "fr": 30,
  "ip": 22,
  "op": 121,
  "w": 360,
  "h": 800,
  "nm": "Working file",
  "ddd": 0,
  "assets": [
    {
      "id": "comp_0",
      "nm": "3.9_transitionary animation 2",
      "fr": 30,
      "layers": [
        {
          "ddd": 0,
          "ind": 1,
          "ty": 3,
          "nm": "Null 1",
          "sr": 1,
          "ks": {
            "o": {
              "a": 0,
              "k": 0,
              "ix": 11
            },
            "r": {
              "a": 0,
              "k": 0,
              "ix": 10
            },
            "p": {
              "a": 0,
              "k": [664, 1475.5, 0],
              "ix": 2,
              "l": 2
            },
            "a": {
              "a": 0,
              "k": [0, 0, 0],
              "ix": 1,
              "l": 2
            },
            "s": {
              "a": 1,
              "k": [
                {
                  "i": {
                    "x": [0.307, 0.307, 0.667],
                    "y": [1, 1, 1]
                  },
                  "o": {
                    "x": [0.333, 0.333, 0.333],
                    "y": [0, 0, 0]
                  },
                  "t": 0,
                  "s": [0, 0, 100]
                },
                {
                  "i": {
                    "x": [0.162, 0.162, 0.667],
                    "y": [1, 1, 1]
                  },
                  "o": {
                    "x": [0.333, 0.333, 0.333],
                    "y": [0, 0, 0]
                  },
                  "t": 15,
                  "s": [110, 110, 100]
                },
                {
                  "t": 19,
                  "s": [100, 100, 100]
                }
              ],
              "ix": 6,
              "l": 2
            }
          },
          "ao": 0,
          "ip": 0,
          "op": 6601,
          "st": 0,
          "bm": 0
        },
        {
          "ddd": 0,
          "ind": 2,
          "ty": 4,
          "nm": "Tick",
          "sr": 1,
          "ks": {
            "o": {
              "a": 0,
              "k": 100,
              "ix": 11
            },
            "r": {
              "a": 0,
              "k": 0,
              "ix": 10
            },
            "p": {
              "a": 0,
              "k": [664.875, 1475.875, 0],
              "ix": 2,
              "l": 2
            },
            "a": {
              "a": 0,
              "k": [0.875, 0.375, 0],
              "ix": 1,
              "l": 2
            },
            "s": {
              "a": 0,
              "k": [100, 100, 100],
              "ix": 6,
              "l": 2
            }
          },
          "ao": 0,
          "shapes": [
            {
              "ty": "gr",
              "it": [
                {
                  "ind": 0,
                  "ty": "sh",
                  "ix": 1,
                  "ks": {
                    "a": 0,
                    "k": {
                      "i": [
                        [0, 0],
                        [0, 0],
                        [0, 0]
                      ],
                      "o": [
                        [0, 0],
                        [0, 0],
                        [0, 0]
                      ],
                      "v": [
                        [-26.5, 5],
                        [-10.75, 20],
                        [28.25, -19]
                      ],
                      "c": false
                    },
                    "ix": 2
                  },
                  "nm": "Path 1",
                  "mn": "ADBE Vector Shape - Group",
                  "hd": false
                },
                {
                  "ty": "st",
                  "c": {
                    "a": 0,
                    "k": [0.941162109375, 0.474517822266, 0.180389404297, 1],
                    "ix": 3
                  },
                  "o": {
                    "a": 0,
                    "k": 100,
                    "ix": 4
                  },
                  "w": {
                    "a": 0,
                    "k": 7,
                    "ix": 5
                  },
                  "lc": 2,
                  "lj": 2,
                  "bm": 0,
                  "nm": "Stroke 1",
                  "mn": "ADBE Vector Graphic - Stroke",
                  "hd": false
                },
                {
                  "ty": "tr",
                  "p": {
                    "a": 0,
                    "k": [0, 0],
                    "ix": 2
                  },
                  "a": {
                    "a": 0,
                    "k": [0, 0],
                    "ix": 1
                  },
                  "s": {
                    "a": 0,
                    "k": [100, 100],
                    "ix": 3
                  },
                  "r": {
                    "a": 0,
                    "k": 0,
                    "ix": 6
                  },
                  "o": {
                    "a": 0,
                    "k": 100,
                    "ix": 7
                  },
                  "sk": {
                    "a": 0,
                    "k": 0,
                    "ix": 4
                  },
                  "sa": {
                    "a": 0,
                    "k": 0,
                    "ix": 5
                  },
                  "nm": "Transform"
                }
              ],
              "nm": "Shape 1",
              "np": 3,
              "cix": 2,
              "bm": 0,
              "ix": 1,
              "mn": "ADBE Vector Group",
              "hd": false
            },
            {
              "ty": "tm",
              "s": {
                "a": 1,
                "k": [
                  {
                    "i": {
                      "x": [0.053],
                      "y": [1]
                    },
                    "o": {
                      "x": [0.333],
                      "y": [0]
                    },
                    "t": 24,
                    "s": [0]
                  },
                  {
                    "t": 30,
                    "s": [100]
                  }
                ],
                "ix": 1
              },
              "e": {
                "a": 0,
                "k": 0,
                "ix": 2
              },
              "o": {
                "a": 0,
                "k": 0,
                "ix": 3
              },
              "m": 1,
              "ix": 2,
              "nm": "Trim Paths 1",
              "mn": "ADBE Vector Filter - Trim",
              "hd": false
            }
          ],
          "ip": 20,
          "op": 6621,
          "st": 20,
          "bm": 0
        },
        {
          "ddd": 0,
          "ind": 3,
          "ty": 4,
          "nm": "White Circle Outlines",
          "sr": 1,
          "ks": {
            "o": {
              "a": 0,
              "k": 100,
              "ix": 11
            },
            "r": {
              "a": 0,
              "k": 0,
              "ix": 10
            },
            "p": {
              "a": 0,
              "k": [663.905, 1475.345, 0],
              "ix": 2,
              "l": 2
            },
            "a": {
              "a": 0,
              "k": [66.25, 66.25, 0],
              "ix": 1,
              "l": 2
            },
            "s": {
              "a": 0,
              "k": [100, 100, 100],
              "ix": 6,
              "l": 2,
              "x": "var $bm_rt;\n$bm_rt = thisComp.layer('Null 1').transform.scale.valueAtTime($bm_sub(time, 0.45));"
            }
          },
          "ao": 0,
          "shapes": [
            {
              "ty": "gr",
              "it": [
                {
                  "ind": 0,
                  "ty": "sh",
                  "ix": 1,
                  "ks": {
                    "a": 0,
                    "k": {
                      "i": [
                        [-36.451, 0],
                        [0, -36.451],
                        [36.451, 0],
                        [0, 36.451]
                      ],
                      "o": [
                        [36.451, 0],
                        [0, 36.451],
                        [-36.451, 0],
                        [0, -36.451]
                      ],
                      "v": [
                        [0, -66],
                        [66, 0],
                        [0, 66],
                        [-66, 0]
                      ],
                      "c": true
                    },
                    "ix": 2
                  },
                  "nm": "Path 1",
                  "mn": "ADBE Vector Shape - Group",
                  "hd": false
                },
                {
                  "ty": "fl",
                  "c": {
                    "a": 0,
                    "k": [1, 1, 1, 1],
                    "ix": 4
                  },
                  "o": {
                    "a": 0,
                    "k": 100,
                    "ix": 5
                  },
                  "r": 1,
                  "bm": 0,
                  "nm": "Fill 1",
                  "mn": "ADBE Vector Graphic - Fill",
                  "hd": false
                },
                {
                  "ty": "tr",
                  "p": {
                    "a": 0,
                    "k": [66.25, 66.25],
                    "ix": 2
                  },
                  "a": {
                    "a": 0,
                    "k": [0, 0],
                    "ix": 1
                  },
                  "s": {
                    "a": 0,
                    "k": [100, 100],
                    "ix": 3
                  },
                  "r": {
                    "a": 0,
                    "k": 0,
                    "ix": 6
                  },
                  "o": {
                    "a": 0,
                    "k": 100,
                    "ix": 7
                  },
                  "sk": {
                    "a": 0,
                    "k": 0,
                    "ix": 4
                  },
                  "sa": {
                    "a": 0,
                    "k": 0,
                    "ix": 5
                  },
                  "nm": "Transform"
                }
              ],
              "nm": "Group 1",
              "np": 2,
              "cix": 2,
              "bm": 0,
              "ix": 1,
              "mn": "ADBE Vector Group",
              "hd": false
            }
          ],
          "ip": 0,
          "op": 6601,
          "st": 0,
          "bm": 0
        },
        {
          "ddd": 0,
          "ind": 4,
          "ty": 4,
          "nm": "1 Outlines",
          "sr": 1,
          "ks": {
            "o": {
              "a": 0,
              "k": 100,
              "ix": 11
            },
            "r": {
              "a": 0,
              "k": 0,
              "ix": 10
            },
            "p": {
              "a": 0,
              "k": [663.905, 1475.345, 0],
              "ix": 2,
              "l": 2
            },
            "a": {
              "a": 0,
              "k": [114.25, 114.25, 0],
              "ix": 1,
              "l": 2
            },
            "s": {
              "a": 0,
              "k": [100, 100, 100],
              "ix": 6,
              "l": 2,
              "x": "var $bm_rt;\n$bm_rt = thisComp.layer('Null 1').transform.scale.valueAtTime($bm_sub(time, 0.4));"
            }
          },
          "ao": 0,
          "shapes": [
            {
              "ty": "gr",
              "it": [
                {
                  "ind": 0,
                  "ty": "sh",
                  "ix": 1,
                  "ks": {
                    "a": 0,
                    "k": {
                      "i": [
                        [-62.96, 0],
                        [0, -62.96],
                        [62.96, 0],
                        [0, 62.96]
                      ],
                      "o": [
                        [62.96, 0],
                        [0, 62.96],
                        [-62.96, 0],
                        [0, -62.96]
                      ],
                      "v": [
                        [0, -114],
                        [114, 0],
                        [0, 114],
                        [-114, 0]
                      ],
                      "c": true
                    },
                    "ix": 2
                  },
                  "nm": "Path 1",
                  "mn": "ADBE Vector Shape - Group",
                  "hd": false
                },
                {
                  "ty": "fl",
                  "c": {
                    "a": 0,
                    "k": [1, 0.643137254902, 0.415686304429, 1],
                    "ix": 4
                  },
                  "o": {
                    "a": 0,
                    "k": 100,
                    "ix": 5
                  },
                  "r": 1,
                  "bm": 0,
                  "nm": "Fill 1",
                  "mn": "ADBE Vector Graphic - Fill",
                  "hd": false
                },
                {
                  "ty": "tr",
                  "p": {
                    "a": 0,
                    "k": [114.25, 114.25],
                    "ix": 2
                  },
                  "a": {
                    "a": 0,
                    "k": [0, 0],
                    "ix": 1
                  },
                  "s": {
                    "a": 0,
                    "k": [100, 100],
                    "ix": 3
                  },
                  "r": {
                    "a": 0,
                    "k": 0,
                    "ix": 6
                  },
                  "o": {
                    "a": 0,
                    "k": 100,
                    "ix": 7
                  },
                  "sk": {
                    "a": 0,
                    "k": 0,
                    "ix": 4
                  },
                  "sa": {
                    "a": 0,
                    "k": 0,
                    "ix": 5
                  },
                  "nm": "Transform"
                }
              ],
              "nm": "Group 1",
              "np": 2,
              "cix": 2,
              "bm": 0,
              "ix": 1,
              "mn": "ADBE Vector Group",
              "hd": false
            }
          ],
          "ip": 0,
          "op": 6601,
          "st": 0,
          "bm": 0
        },
        {
          "ddd": 0,
          "ind": 5,
          "ty": 4,
          "nm": "Line 1 Outlines",
          "sr": 1,
          "ks": {
            "o": {
              "a": 0,
              "k": 100,
              "ix": 11
            },
            "r": {
              "a": 0,
              "k": 0,
              "ix": 10
            },
            "p": {
              "a": 0,
              "k": [663.905, 1475.345, 0],
              "ix": 2,
              "l": 2
            },
            "a": {
              "a": 0,
              "k": [166.5, 166.5, 0],
              "ix": 1,
              "l": 2
            },
            "s": {
              "a": 0,
              "k": [100, 100, 100],
              "ix": 6,
              "l": 2,
              "x": "var $bm_rt;\n$bm_rt = thisComp.layer('Null 1').transform.scale.valueAtTime($bm_sub(time, 0.7));"
            }
          },
          "ao": 0,
          "shapes": [
            {
              "ty": "gr",
              "it": [
                {
                  "ind": 0,
                  "ty": "sh",
                  "ix": 1,
                  "ks": {
                    "a": 0,
                    "k": {
                      "i": [
                        [-91.403, 0],
                        [0, -91.403],
                        [91.403, 0],
                        [0, 91.403]
                      ],
                      "o": [
                        [91.403, 0],
                        [0, 91.403],
                        [-91.403, 0],
                        [0, -91.403]
                      ],
                      "v": [
                        [0, -165.5],
                        [165.5, 0],
                        [0, 165.5],
                        [-165.5, 0]
                      ],
                      "c": true
                    },
                    "ix": 2
                  },
                  "nm": "Path 1",
                  "mn": "ADBE Vector Shape - Group",
                  "hd": false
                },
                {
                  "ty": "st",
                  "c": {
                    "a": 0,
                    "k": [0.968627510819, 0.713725490196, 0.552941176471, 1],
                    "ix": 3
                  },
                  "o": {
                    "a": 0,
                    "k": 100,
                    "ix": 4
                  },
                  "w": {
                    "a": 0,
                    "k": 1,
                    "ix": 5
                  },
                  "lc": 1,
                  "lj": 1,
                  "ml": 4,
                  "bm": 0,
                  "nm": "Stroke 1",
                  "mn": "ADBE Vector Graphic - Stroke",
                  "hd": false
                },
                {
                  "ty": "tr",
                  "p": {
                    "a": 0,
                    "k": [166.5, 166.5],
                    "ix": 2
                  },
                  "a": {
                    "a": 0,
                    "k": [0, 0],
                    "ix": 1
                  },
                  "s": {
                    "a": 0,
                    "k": [100, 100],
                    "ix": 3
                  },
                  "r": {
                    "a": 0,
                    "k": 0,
                    "ix": 6
                  },
                  "o": {
                    "a": 0,
                    "k": 100,
                    "ix": 7
                  },
                  "sk": {
                    "a": 0,
                    "k": 0,
                    "ix": 4
                  },
                  "sa": {
                    "a": 0,
                    "k": 0,
                    "ix": 5
                  },
                  "nm": "Transform"
                }
              ],
              "nm": "Group 1",
              "np": 2,
              "cix": 2,
              "bm": 0,
              "ix": 1,
              "mn": "ADBE Vector Group",
              "hd": false
            }
          ],
          "ip": 0,
          "op": 6601,
          "st": 0,
          "bm": 0
        },
        {
          "ddd": 0,
          "ind": 6,
          "ty": 4,
          "nm": "2 Outlines",
          "sr": 1,
          "ks": {
            "o": {
              "a": 0,
              "k": 100,
              "ix": 11
            },
            "r": {
              "a": 0,
              "k": 0,
              "ix": 10
            },
            "p": {
              "a": 0,
              "k": [663.905, 1475.345, 0],
              "ix": 2,
              "l": 2
            },
            "a": {
              "a": 0,
              "k": [224.25, 224.25, 0],
              "ix": 1,
              "l": 2
            },
            "s": {
              "a": 0,
              "k": [100, 100, 100],
              "ix": 6,
              "l": 2,
              "x": "var $bm_rt;\n$bm_rt = thisComp.layer('Null 1').transform.scale.valueAtTime($bm_sub(time, 0.3));"
            }
          },
          "ao": 0,
          "shapes": [
            {
              "ty": "gr",
              "it": [
                {
                  "ind": 0,
                  "ty": "sh",
                  "ix": 1,
                  "ks": {
                    "a": 0,
                    "k": {
                      "i": [
                        [-123.712, 0],
                        [0, -123.712],
                        [123.712, 0],
                        [0, 123.712]
                      ],
                      "o": [
                        [123.712, 0],
                        [0, 123.712],
                        [-123.712, 0],
                        [0, -123.712]
                      ],
                      "v": [
                        [0, -224],
                        [224, 0],
                        [0, 224],
                        [-224, 0]
                      ],
                      "c": true
                    },
                    "ix": 2
                  },
                  "nm": "Path 1",
                  "mn": "ADBE Vector Shape - Group",
                  "hd": false
                },
                {
                  "ty": "fl",
                  "c": {
                    "a": 0,
                    "k": [0.972549079446, 0.541176470588, 0.266666666667, 1],
                    "ix": 4
                  },
                  "o": {
                    "a": 0,
                    "k": 100,
                    "ix": 5
                  },
                  "r": 1,
                  "bm": 0,
                  "nm": "Fill 1",
                  "mn": "ADBE Vector Graphic - Fill",
                  "hd": false
                },
                {
                  "ty": "tr",
                  "p": {
                    "a": 0,
                    "k": [224.25, 224.25],
                    "ix": 2
                  },
                  "a": {
                    "a": 0,
                    "k": [0, 0],
                    "ix": 1
                  },
                  "s": {
                    "a": 0,
                    "k": [100, 100],
                    "ix": 3
                  },
                  "r": {
                    "a": 0,
                    "k": 0,
                    "ix": 6
                  },
                  "o": {
                    "a": 0,
                    "k": 100,
                    "ix": 7
                  },
                  "sk": {
                    "a": 0,
                    "k": 0,
                    "ix": 4
                  },
                  "sa": {
                    "a": 0,
                    "k": 0,
                    "ix": 5
                  },
                  "nm": "Transform"
                }
              ],
              "nm": "Group 1",
              "np": 2,
              "cix": 2,
              "bm": 0,
              "ix": 1,
              "mn": "ADBE Vector Group",
              "hd": false
            }
          ],
          "ip": 0,
          "op": 6601,
          "st": 0,
          "bm": 0
        },
        {
          "ddd": 0,
          "ind": 7,
          "ty": 4,
          "nm": "Line 2 Outlines",
          "sr": 1,
          "ks": {
            "o": {
              "a": 0,
              "k": 100,
              "ix": 11
            },
            "r": {
              "a": 0,
              "k": 0,
              "ix": 10
            },
            "p": {
              "a": 0,
              "k": [663.905, 1475.345, 0],
              "ix": 2,
              "l": 2
            },
            "a": {
              "a": 0,
              "k": [285.5, 285.5, 0],
              "ix": 1,
              "l": 2
            },
            "s": {
              "a": 0,
              "k": [100, 100, 100],
              "ix": 6,
              "l": 2,
              "x": "var $bm_rt;\n$bm_rt = thisComp.layer('Null 1').transform.scale.valueAtTime($bm_sub(time, 0.5));"
            }
          },
          "ao": 0,
          "shapes": [
            {
              "ty": "gr",
              "it": [
                {
                  "ind": 0,
                  "ty": "sh",
                  "ix": 1,
                  "ks": {
                    "a": 0,
                    "k": {
                      "i": [
                        [-157.125, 0],
                        [0, -157.125],
                        [157.125, 0],
                        [0, 157.125]
                      ],
                      "o": [
                        [157.125, 0],
                        [0, 157.125],
                        [-157.125, 0],
                        [0, -157.125]
                      ],
                      "v": [
                        [0, -284.5],
                        [284.5, 0],
                        [0, 284.5],
                        [-284.5, 0]
                      ],
                      "c": true
                    },
                    "ix": 2
                  },
                  "nm": "Path 1",
                  "mn": "ADBE Vector Shape - Group",
                  "hd": false
                },
                {
                  "ty": "st",
                  "c": {
                    "a": 0,
                    "k": [0.952941236309, 0.592156862745, 0.364705882353, 1],
                    "ix": 3
                  },
                  "o": {
                    "a": 0,
                    "k": 100,
                    "ix": 4
                  },
                  "w": {
                    "a": 0,
                    "k": 1,
                    "ix": 5
                  },
                  "lc": 1,
                  "lj": 1,
                  "ml": 4,
                  "bm": 0,
                  "nm": "Stroke 1",
                  "mn": "ADBE Vector Graphic - Stroke",
                  "hd": false
                },
                {
                  "ty": "tr",
                  "p": {
                    "a": 0,
                    "k": [285.5, 285.5],
                    "ix": 2
                  },
                  "a": {
                    "a": 0,
                    "k": [0, 0],
                    "ix": 1
                  },
                  "s": {
                    "a": 0,
                    "k": [100, 100],
                    "ix": 3
                  },
                  "r": {
                    "a": 0,
                    "k": 0,
                    "ix": 6
                  },
                  "o": {
                    "a": 0,
                    "k": 100,
                    "ix": 7
                  },
                  "sk": {
                    "a": 0,
                    "k": 0,
                    "ix": 4
                  },
                  "sa": {
                    "a": 0,
                    "k": 0,
                    "ix": 5
                  },
                  "nm": "Transform"
                }
              ],
              "nm": "Group 1",
              "np": 2,
              "cix": 2,
              "bm": 0,
              "ix": 1,
              "mn": "ADBE Vector Group",
              "hd": false
            }
          ],
          "ip": 0,
          "op": 6601,
          "st": 0,
          "bm": 0
        },
        {
          "ddd": 0,
          "ind": 8,
          "ty": 4,
          "nm": "3 Outlines",
          "sr": 1,
          "ks": {
            "o": {
              "a": 0,
              "k": 100,
              "ix": 11
            },
            "r": {
              "a": 0,
              "k": 0,
              "ix": 10
            },
            "p": {
              "a": 0,
              "k": [663.905, 1475.345, 0],
              "ix": 2,
              "l": 2
            },
            "a": {
              "a": 0,
              "k": [353.25, 353.25, 0],
              "ix": 1,
              "l": 2
            },
            "s": {
              "a": 0,
              "k": [100, 100, 100],
              "ix": 6,
              "l": 2,
              "x": "var $bm_rt;\n$bm_rt = thisComp.layer('Null 1').transform.scale.valueAtTime($bm_sub(time, 0.2));"
            }
          },
          "ao": 0,
          "shapes": [
            {
              "ty": "gr",
              "it": [
                {
                  "ind": 0,
                  "ty": "sh",
                  "ix": 1,
                  "ks": {
                    "a": 0,
                    "k": {
                      "i": [
                        [-194.957, 0],
                        [0, -194.957],
                        [194.956, 0],
                        [0, 194.957]
                      ],
                      "o": [
                        [194.956, 0],
                        [0, 194.957],
                        [-194.957, 0],
                        [0, -194.957]
                      ],
                      "v": [
                        [0, -353],
                        [353, 0],
                        [0, 353],
                        [-353, 0]
                      ],
                      "c": true
                    },
                    "ix": 2
                  },
                  "nm": "Path 1",
                  "mn": "ADBE Vector Shape - Group",
                  "hd": false
                },
                {
                  "ty": "fl",
                  "c": {
                    "a": 0,
                    "k": [0.909803981407, 0.423529441684, 0.176470588235, 1],
                    "ix": 4
                  },
                  "o": {
                    "a": 0,
                    "k": 100,
                    "ix": 5
                  },
                  "r": 1,
                  "bm": 0,
                  "nm": "Fill 1",
                  "mn": "ADBE Vector Graphic - Fill",
                  "hd": false
                },
                {
                  "ty": "tr",
                  "p": {
                    "a": 0,
                    "k": [353.25, 353.25],
                    "ix": 2
                  },
                  "a": {
                    "a": 0,
                    "k": [0, 0],
                    "ix": 1
                  },
                  "s": {
                    "a": 0,
                    "k": [100, 100],
                    "ix": 3
                  },
                  "r": {
                    "a": 0,
                    "k": 0,
                    "ix": 6
                  },
                  "o": {
                    "a": 0,
                    "k": 100,
                    "ix": 7
                  },
                  "sk": {
                    "a": 0,
                    "k": 0,
                    "ix": 4
                  },
                  "sa": {
                    "a": 0,
                    "k": 0,
                    "ix": 5
                  },
                  "nm": "Transform"
                }
              ],
              "nm": "Group 1",
              "np": 2,
              "cix": 2,
              "bm": 0,
              "ix": 1,
              "mn": "ADBE Vector Group",
              "hd": false
            }
          ],
          "ip": 0,
          "op": 6601,
          "st": 0,
          "bm": 0
        },
        {
          "ddd": 0,
          "ind": 9,
          "ty": 4,
          "nm": "Line 3 Outlines",
          "sr": 1,
          "ks": {
            "o": {
              "a": 0,
              "k": 100,
              "ix": 11
            },
            "r": {
              "a": 0,
              "k": 0,
              "ix": 10
            },
            "p": {
              "a": 0,
              "k": [663.905, 1475.345, 0],
              "ix": 2,
              "l": 2
            },
            "a": {
              "a": 0,
              "k": [404.5, 404.5, 0],
              "ix": 1,
              "l": 2
            },
            "s": {
              "a": 0,
              "k": [100, 100, 100],
              "ix": 6,
              "l": 2,
              "x": "var $bm_rt;\n$bm_rt = thisComp.layer('Null 1').transform.scale.valueAtTime($bm_sub(time, 0.3));"
            }
          },
          "ao": 0,
          "shapes": [
            {
              "ty": "gr",
              "it": [
                {
                  "ind": 0,
                  "ty": "sh",
                  "ix": 1,
                  "ks": {
                    "a": 0,
                    "k": {
                      "i": [
                        [-222.847, 0],
                        [0, -222.847],
                        [222.847, 0],
                        [0, 222.847]
                      ],
                      "o": [
                        [222.847, 0],
                        [0, 222.847],
                        [-222.847, 0],
                        [0, -222.847]
                      ],
                      "v": [
                        [0, -403.5],
                        [403.5, 0],
                        [0, 403.5],
                        [-403.5, 0]
                      ],
                      "c": true
                    },
                    "ix": 2
                  },
                  "nm": "Path 1",
                  "mn": "ADBE Vector Shape - Group",
                  "hd": false
                },
                {
                  "ty": "st",
                  "c": {
                    "a": 0,
                    "k": [0.952941236309, 0.592156862745, 0.364705882353, 1],
                    "ix": 3
                  },
                  "o": {
                    "a": 0,
                    "k": 100,
                    "ix": 4
                  },
                  "w": {
                    "a": 0,
                    "k": 1,
                    "ix": 5
                  },
                  "lc": 1,
                  "lj": 1,
                  "ml": 4,
                  "bm": 0,
                  "nm": "Stroke 1",
                  "mn": "ADBE Vector Graphic - Stroke",
                  "hd": false
                },
                {
                  "ty": "tr",
                  "p": {
                    "a": 0,
                    "k": [404.5, 404.5],
                    "ix": 2
                  },
                  "a": {
                    "a": 0,
                    "k": [0, 0],
                    "ix": 1
                  },
                  "s": {
                    "a": 0,
                    "k": [100, 100],
                    "ix": 3
                  },
                  "r": {
                    "a": 0,
                    "k": 0,
                    "ix": 6
                  },
                  "o": {
                    "a": 0,
                    "k": 100,
                    "ix": 7
                  },
                  "sk": {
                    "a": 0,
                    "k": 0,
                    "ix": 4
                  },
                  "sa": {
                    "a": 0,
                    "k": 0,
                    "ix": 5
                  },
                  "nm": "Transform"
                }
              ],
              "nm": "Group 1",
              "np": 2,
              "cix": 2,
              "bm": 0,
              "ix": 1,
              "mn": "ADBE Vector Group",
              "hd": false
            }
          ],
          "ip": 0,
          "op": 6601,
          "st": 0,
          "bm": 0
        },
        {
          "ddd": 0,
          "ind": 10,
          "ty": 4,
          "nm": "4 Outlines",
          "sr": 1,
          "ks": {
            "o": {
              "a": 0,
              "k": 100,
              "ix": 11
            },
            "r": {
              "a": 0,
              "k": 0,
              "ix": 10
            },
            "p": {
              "a": 0,
              "k": [663.905, 1480.345, 0],
              "ix": 2,
              "l": 2
            },
            "a": {
              "a": 0,
              "k": [630.25, 630.25, 0],
              "ix": 1,
              "l": 2
            },
            "s": {
              "a": 0,
              "k": [100, 100, 100],
              "ix": 6,
              "l": 2,
              "x": "var $bm_rt;\n$bm_rt = thisComp.layer('Null 1').transform.scale;"
            }
          },
          "ao": 0,
          "shapes": [
            {
              "ty": "gr",
              "it": [
                {
                  "ind": 0,
                  "ty": "sh",
                  "ix": 1,
                  "ks": {
                    "a": 0,
                    "k": {
                      "i": [
                        [-347.939, 0],
                        [0, -347.939],
                        [347.939, 0],
                        [0, 347.939]
                      ],
                      "o": [
                        [347.939, 0],
                        [0, 347.939],
                        [-347.939, 0],
                        [0, -347.939]
                      ],
                      "v": [
                        [0, -630],
                        [630, 0],
                        [0, 630],
                        [-630, 0]
                      ],
                      "c": true
                    },
                    "ix": 2
                  },
                  "nm": "Path 1",
                  "mn": "ADBE Vector Shape - Group",
                  "hd": false
                },
                {
                  "ty": "fl",
                  "c": {
                    "a": 0,
                    "k": [0.941176530427, 0.447058853449, 0.196078446332, 1],
                    "ix": 4
                  },
                  "o": {
                    "a": 0,
                    "k": 100,
                    "ix": 5
                  },
                  "r": 1,
                  "bm": 0,
                  "nm": "Fill 1",
                  "mn": "ADBE Vector Graphic - Fill",
                  "hd": false
                },
                {
                  "ty": "tr",
                  "p": {
                    "a": 0,
                    "k": [630.25, 630.25],
                    "ix": 2
                  },
                  "a": {
                    "a": 0,
                    "k": [0, 0],
                    "ix": 1
                  },
                  "s": {
                    "a": 0,
                    "k": [100, 100],
                    "ix": 3
                  },
                  "r": {
                    "a": 0,
                    "k": 0,
                    "ix": 6
                  },
                  "o": {
                    "a": 0,
                    "k": 100,
                    "ix": 7
                  },
                  "sk": {
                    "a": 0,
                    "k": 0,
                    "ix": 4
                  },
                  "sa": {
                    "a": 0,
                    "k": 0,
                    "ix": 5
                  },
                  "nm": "Transform"
                }
              ],
              "nm": "Group 1",
              "np": 2,
              "cix": 2,
              "bm": 0,
              "ix": 1,
              "mn": "ADBE Vector Group",
              "hd": false
            }
          ],
          "ip": 0,
          "op": 6601,
          "st": 0,
          "bm": 0
        }
      ]
    }
  ],
  "layers": [
    {
      "ddd": 0,
      "ind": 1,
      "ty": 0,
      "nm": "3.9_transitionary animation 2",
      "cl": "9_transitionary",
      "refId": "comp_0",
      "sr": 1,
      "ks": {
        "o": {
          "a": 1,
          "k": [
            {
              "i": {
                "x": [0.833],
                "y": [0.833]
              },
              "o": {
                "x": [0.167],
                "y": [0.167]
              },
              "t": 91,
              "s": [100]
            },
            {
              "t": 104,
              "s": [0]
            }
          ],
          "ix": 11
        },
        "r": {
          "a": 0,
          "k": 0,
          "ix": 10
        },
        "p": {
          "a": 0,
          "k": [180, 400, 0],
          "ix": 2,
          "l": 2
        },
        "a": {
          "a": 0,
          "k": [664, 1475.5, 0],
          "ix": 1,
          "l": 2
        },
        "s": {
          "a": 0,
          "k": [100, 100, 100],
          "ix": 6,
          "l": 2
        }
      },
      "ao": 0,
      "w": 1328,
      "h": 2951,
      "ip": 30,
      "op": 6631,
      "st": 30,
      "bm": 0
    }
  ],
  "markers": []
}
